gitee_deleter/__init__.py
gitee_deleter/remove_all.py
gitee_deleter/utils.py
gitee_deleter-0.0.2.dist-info/LICENSE
gitee_deleter-0.0.2.dist-info/METADATA
gitee_deleter-0.0.2.dist-info/WHEEL
gitee_deleter-0.0.2.dist-info/top_level.txt
gitee_deleter-0.0.2.dist-info/RECORD
