Metadata-Version: 2.1
Name: gitee-deleter
Version: 0.0.2
Summary: 一键删光 Gitee 个人项目，非常垂直的账号注销脚本
Home-page: https://github.com/QIN2DIM/gitee-deleter
Author: QIN2DIM
Author-email: rmalkaid@outlook.com
License: Apache License 2.0
Keywords: gitee,gitee-deleter
Platform: UNKNOWN
Classifier: Topic :: Scientific/Engineering
Classifier: Topic :: Scientific/Engineering :: Artificial Intelligence
Classifier: Topic :: Software Development
Classifier: Topic :: Software Development :: Libraries
Classifier: Topic :: Software Development :: Libraries :: Python Modules
Classifier: License :: OSI Approved :: Apache Software License
Classifier: Programming Language :: Python :: 3
Requires-Python: >=3.8
License-File: LICENSE
Requires-Dist: pyyaml (~=6.0)
Requires-Dist: selenium (~=4.1.0)
Requires-Dist: loguru (~=0.6.0)
Requires-Dist: cloudscraper (~=1.2.58)
Requires-Dist: lxml (~=4.7.1)
Requires-Dist: webdriver-manager (>=3.5.2)
